pyunicoremanager/__init__.py
pyunicoremanager/core.py
pyunicoremanager-0.0.4.dist-info/LICENSE
pyunicoremanager-0.0.4.dist-info/METADATA
pyunicoremanager-0.0.4.dist-info/WHEEL
pyunicoremanager-0.0.4.dist-info/top_level.txt
pyunicoremanager-0.0.4.dist-info/RECORD
