Metadata-Version: 2.1
Name: pyunicoremanager
Version: 0.0.4
Summary: Python wrapper of PyUnicore to deploy jobs on UNICORE systems
Home-page: https://github.com/aperezmartin/PyUnicoreManager
Author: =?utf-8?b?QWFyw7NuIFDDqXJleiBNYXJ0w61u?=
Author-email: a.perez.martin@fz-juelich.de
Classifier: Programming Language :: Python :: 3
Classifier: License :: OSI Approved :: MIT License
Requires-Python: >=3.6
License-File: LICENSE
